{
    "$schema": "https://zed.dev/schema/themes/v0.2.0.json",
    "name": "Dynamic Base16 DankShell",
    "author": "Adarsh219",
    "themes": [
        {
            "name": "DankShell Dark",
            "appearance": "dark",
            "style": {
                "accents": [
                    "#c4c0ff",
                    "#c7c4dc",
                    "#eab9d1"
                ],
                "background.appearance": "opaque",
                "border": "#47464f",
                "border.variant": "#928f99",
                "border.focused": "#c4c0ff",
                "border.selected": "#c4c0ff",
                "border.transparent": null,
                "border.disabled": "#47464f60",
                "elevated_surface.background": "#2a292f",
                "surface.background": "#131318",
                "background": "#131318",
                "element.background": "#201f25",
                "element.hover": "#2a292f",
                "element.active": "#35343a",
                "element.selected": "#464559",
                "element.disabled": "#47464f",
                "drop_target.background": "#43407880",
                "ghost_element.background": null,
                "ghost_element.hover": "#201f2580",
                "ghost_element.active": "#2a292f",
                "ghost_element.selected": "#46455980",
                "ghost_element.disabled": "#47464f60",
                "text": "#e5e1e9",
                "text.muted": "#c8c5d0",
                "text.placeholder": "#c8c5d099",
                "text.disabled": "#e5e1e960",
                "text.accent": "#c4c0ff",
                "icon": "#e5e1e9",
                "icon.muted": "#c8c5d0",
                "icon.disabled": "#e5e1e960",
                "icon.placeholder": "#c8c5d080",
                "icon.accent": "#c4c0ff",
                "status_bar.background": "#131318",
                "title_bar.background": "#131318",
                "title_bar.inactive_background": "#131318",
                "toolbar.background": "#131318",
                "tab_bar.background": "#131318",
                "tab.inactive_background": "#131318",
                "tab.active_background": "#131318",
                "search.match_background": "#ffd87250",
                "search.active_match_background": "#ff9fb566",
                "panel.background": "#131318",
                "panel.focused_border": null,
                "pane.focused_border": null,
                "scrollbar.thumb.background": "#c8c5d050",
                "scrollbar.thumb.hover_background": "#c8c5d080",
                "scrollbar.thumb.border": "#47464f40",
                "scrollbar.track.background": null,
                "scrollbar.track.border": "#47464f20",
                "editor.foreground": "#e5e1e9",
                "editor.background": "#131318",
                "editor.gutter.background": "#131318",
                "editor.subheader.background": "#131318",
                "editor.indent_guide": "#47464f22",
                "editor.indent_guide_active": "#c4c0ff99",
                "editor.active_line.background": "#201f2566",
                "editor.highlighted_line.background": "#201f2566",
                "editor.line_number": "#c8c5d0",
                "editor.active_line_number": "#c4c0ff",
                "editor.invisible": "#47464f33",
                "editor.wrap_guide": "#47464f22",
                "editor.active_wrap_guide": "#928f9980",
                "editor.document_highlight.read_background": "#43407860",
                "editor.document_highlight.write_background": "#46455980",
                "terminal.background": "#131318",
                "terminal.foreground": "#e5e1e9",
                "terminal.bright_foreground": "#f8f8ff",
                "terminal.dim_foreground": "#c8c5d0",
                "terminal.ansi.black": "#131318",
                "terminal.ansi.bright_black": "#9a99a5",
                "terminal.ansi.dim_black": "#131318",
                "terminal.ansi.red": "#ff7293",
                "terminal.ansi.bright_red": "#ff9fb5",
                "terminal.ansi.dim_red": "#ff7293",
                "terminal.ansi.green": "#7fff97",
                "terminal.ansi.bright_green": "#a5ffb6",
                "terminal.ansi.dim_green": "#7fff97",
                "terminal.ansi.yellow": "#ffd872",
                "terminal.ansi.bright_yellow": "#ffe6a5",
                "terminal.ansi.dim_yellow": "#ffd872",
                "terminal.ansi.blue": "#aeaaf2",
                "terminal.ansi.bright_blue": "#ccc9ff",
                "terminal.ansi.dim_blue": "#aeaaf2",
                "terminal.ansi.magenta": "#434076",
                "terminal.ansi.bright_magenta": "#d5d2ff",
                "terminal.ansi.dim_magenta": "#434076",
                "terminal.ansi.cyan": "#c4c0ff",
                "terminal.ansi.bright_cyan": "#e4e2ff",
                "terminal.ansi.dim_cyan": "#c4c0ff",
                "terminal.ansi.white": "#f0efff",
                "terminal.ansi.bright_white": "#f8f8ff",
                "terminal.ansi.dim_white": "#f0efff",
                "link_text.hover": "#c4c0ff",
                "version_control.added": "#7fff97",
                "version_control.modified": "#ffd872",
                "version_control.word_added": "#7fff9733",
                "version_control.word_deleted": "#ff729333",
                "version_control.deleted": "#ff7293",
                "conflict": "#ffb4ab",
                "conflict.background": "#93000a80",
                "conflict.border": "#ffdad6",
                "created": "#7fff97",
                "created.background": "#7fff971A",
                "created.border": "#7fff97",
                "deleted": "#ff7293",
                "deleted.background": "#ff72931A",
                "deleted.border": "#ff7293",
                "error": "#ffb4ab",
                "error.background": "#93000a",
                "error.border": "#ffdad6",
                "hidden": "#47464f",
                "hidden.background": "#47464f1A",
                "hidden.border": "#47464f60",
                "hint": "#c4c0ff",
                "hint.background": "#43407880",
                "hint.border": "#e3dfff",
                "ignored": "#c8c5d060",
                "ignored.background": "#47464f40",
                "ignored.border": "#47464f40",
                "info": "#c4c0ff",
                "info.background": "#43407880",
                "info.border": "#e3dfff",
                "modified": "#ffd872",
                "modified.background": "#ffd8721A",
                "modified.border": "#ffd872",
                "predictive": "#c8c5d080",
                "predictive.border": "#928f99",
                "predictive.background": "#35343a80",
                "renamed": "#aeaaf2",
                "renamed.border": "#aeaaf2",
                "renamed.background": "#aeaaf21A",
                "success": "#7fff97",
                "success.background": "#7fff971A",
                "success.border": "#7fff97",
                "unreachable": "#c8c5d060",
                "unreachable.background": "#47464f40",
                "unreachable.border": "#47464f60",
                "warning": "#eab9d1",
                "warning.background": "#603b4f80",
                "warning.border": "#ffd8e9",
                "players": [
                    {
                        "cursor": "#aeaaf2",
                        "background": "#aeaaf280",
                        "selection": "#aeaaf23D"
                    },
                    {
                        "cursor": "#ff7293",
                        "background": "#ff729380",
                        "selection": "#ff72933D"
                    },
                    {
                        "cursor": "#ffd872",
                        "background": "#ffd87280",
                        "selection": "#ffd8723D"
                    },
                    {
                        "cursor": "#434076",
                        "background": "#43407680",
                        "selection": "#4340763D"
                    },
                    {
                        "cursor": "#c4c0ff",
                        "background": "#c4c0ff80",
                        "selection": "#c4c0ff3D"
                    },
                    {
                        "cursor": "#ff9fb5",
                        "background": "#ff9fb580",
                        "selection": "#ff9fb53D"
                    },
                    {
                        "cursor": "#a5ffb6",
                        "background": "#a5ffb680",
                        "selection": "#a5ffb63D"
                    },
                    {
                        "cursor": "#7fff97",
                        "background": "#7fff9780",
                        "selection": "#7fff973D"
                    }
                ],
                "syntax": {
                    "attribute": {
                        "color": "#aeaaf2",
                        "font_style": "italic",
                        "font_weight": null
                    },
                    "boolean": {
                        "color": "#ff9fb5",
                        "font_style": null,
                        "font_weight": null
                    },
                    "comment": {
                        "color": "#9a99a5",
                        "font_style": "italic",
                        "font_weight": null
                    },
                    "comment.doc": {
                        "color": "#9a99a5",
                        "font_style": "italic",
                        "font_weight": null
                    },
                    "constant": {
                        "color": "#ff9fb5",
                        "font_style": null,
                        "font_weight": null
                    },
                    "constructor": {
                        "color": "#aeaaf2",
                        "font_style": null,
                        "font_weight": null
                    },
                    "embedded": {
                        "color": "#e5e1e9",
                        "font_style": null,
                        "font_weight": null
                    },
                    "emphasis": {
                        "color": "#aeaaf2",
                        "font_style": "italic",
                        "font_weight": null
                    },
                    "emphasis.strong": {
                        "color": "#ff9fb5",
                        "font_style": null,
                        "font_weight": 700
                    },
                    "enum": {
                        "color": "#c4c0ff",
                        "font_style": null,
                        "font_weight": null
                    },
                    "function": {
                        "color": "#aeaaf2",
                        "font_style": null,
                        "font_weight": null
                    },
                    "keyword": {
                        "color": "#434076",
                        "font_style": "italic",
                        "font_weight": null
                    },
                    "label": {
                        "color": "#aeaaf2",
                        "font_style": null,
                        "font_weight": null
                    },
                    "link_text": {
                        "color": "#aeaaf2",
                        "font_style": "italic",
                        "font_weight": null
                    },
                    "link_uri": {
                        "color": "#c4c0ff",
                        "font_style": "normal",
                        "font_weight": null
                    },
                    "number": {
                        "color": "#ff9fb5",
                        "font_style": null,
                        "font_weight": null
                    },
                    "operator": {
                        "color": "#c4c0ff",
                        "font_style": null,
                        "font_weight": null
                    },
                    "property": {
                        "color": "#ff7293",
                        "font_style": null,
                        "font_weight": null
                    },
                    "punctuation": {
                        "color": "#c8c5d0",
                        "font_style": null,
                        "font_weight": null
                    },
                    "punctuation.bracket": {
                        "color": "#928f99",
                        "font_style": null,
                        "font_weight": null
                    },
                    "punctuation.delimiter": {
                        "color": "#928f99",
                        "font_style": null,
                        "font_weight": null
                    },
                    "punctuation.list_marker": {
                        "color": "#ff7293",
                        "font_style": null,
                        "font_weight": null
                    },
                    "punctuation.special": {
                        "color": "#ff7293",
                        "font_style": null,
                        "font_weight": null
                    },
                    "selector": {
                        "color": "#ffd872",
                        "font_style": null,
                        "font_weight": null
                    },
                    "selector.pseudo": {
                        "color": "#aeaaf2",
                        "font_style": null,
                        "font_weight": null
                    },
                    "string": {
                        "color": "#7fff97",
                        "font_style": null,
                        "font_weight": null
                    },
                    "string.escape": {
                        "color": "#c4c0ff",
                        "font_style": null,
                        "font_weight": null
                    },
                    "string.regex": {
                        "color": "#a5ffb6",
                        "font_style": null,
                        "font_weight": null
                    },
                    "string.special": {
                        "color": "#c4c0ff",
                        "font_style": null,
                        "font_weight": null
                    },
                    "string.special.symbol": {
                        "color": "#c4c0ff",
                        "font_style": null,
                        "font_weight": null
                    },
                    "tag": {
                        "color": "#aeaaf2",
                        "font_style": null,
                        "font_weight": null
                    },
                    "text.literal": {
                        "color": "#7fff97",
                        "font_style": null,
                        "font_weight": null
                    },
                    "title": {
                        "color": "#ff7293",
                        "font_style": null,
                        "font_weight": 700
                    },
                    "type": {
                        "color": "#ffd872",
                        "font_style": "italic",
                        "font_weight": null
                    },
                    "variable": {
                        "color": "#e5e1e9",
                        "font_style": null,
                        "font_weight": null
                    },
                    "variable.special": {
                        "color": "#ff9fb5",
                        "font_style": null,
                        "font_weight": null
                    },
                    "variant": {
                        "color": "#aeaaf2",
                        "font_style": null,
                        "font_weight": null
                    }
                }
            }
        },
        {
            "name": "DankShell Light",
            "appearance": "light",
            "style": {
                "accents": [
                    "#5b5891",
                    "#5e5c71",
                    "#7a5367"
                ],
                "background.appearance": "opaque",
                "border": "#c8c5d0",
                "border.variant": "#787680",
                "border.focused": "#5b5891",
                "border.selected": "#5b5891",
                "border.transparent": null,
                "border.disabled": "#c8c5d060",
                "elevated_surface.background": "#ebe7ef",
                "surface.background": "#fcf8ff",
                "background": "#dcd8e0",
                "element.background": "#f0ecf4",
                "element.hover": "#ebe7ef",
                "element.active": "#e5e1e9",
                "element.selected": "#e3e0f9",
                "element.disabled": "#e5e1ec",
                "drop_target.background": "#e3dfff80",
                "ghost_element.background": null,
                "ghost_element.hover": "#f0ecf480",
                "ghost_element.active": "#ebe7ef",
                "ghost_element.selected": "#e3e0f980",
                "ghost_element.disabled": "#e5e1ec60",
                "text": "#1c1b21",
                "text.muted": "#47464f",
                "text.placeholder": "#47464f99",
                "text.disabled": "#1c1b2160",
                "text.accent": "#5b5891",
                "icon": "#1c1b21",
                "icon.muted": "#47464f",
                "icon.disabled": "#1c1b2160",
                "icon.placeholder": "#47464f80",
                "icon.accent": "#5b5891",
                "status_bar.background": "#dcd8e0",
                "title_bar.background": "#dcd8e0",
                "title_bar.inactive_background": "#dcd8e0",
                "toolbar.background": "#fcf8ff",
                "tab_bar.background": "#fcf8ff",
                "tab.inactive_background": "#fcf8ff",
                "tab.active_background": "#fcf8ff",
                "search.match_background": "#ad8a2b50",
                "search.active_match_background": "#ad566b66",
                "panel.background": "#fcf8ff",
                "panel.focused_border": null,
                "pane.focused_border": null,
                "scrollbar.thumb.background": "#47464f50",
                "scrollbar.thumb.hover_background": "#47464fC0",
                "scrollbar.thumb.border": "#c8c5d040",
                "scrollbar.track.background": null,
                "scrollbar.track.border": "#c8c5d020",
                "editor.foreground": "#1c1b21",
                "editor.background": "#fcf8ff",
                "editor.gutter.background": "#dcd8e0",
                "editor.subheader.background": "#fcf8ff",
                "editor.indent_guide": "#c8c5d022",
                "editor.indent_guide_active": "#78768099",
                "editor.active_line.background": "#f0ecf466",
                "editor.highlighted_line.background": "#f0ecf466",
                "editor.line_number": "#47464f",
                "editor.active_line_number": "#5b5891",
                "editor.invisible": "#c8c5d033",
                "editor.wrap_guide": "#c8c5d022",
                "editor.active_wrap_guide": "#78768080",
                "editor.document_highlight.read_background": "#e3dfff60",
                "editor.document_highlight.write_background": "#e3e0f980",
                "terminal.background": "#fcf8ff",
                "terminal.foreground": "#1c1b21",
                "terminal.bright_foreground": "#d5d5d9",
                "terminal.dim_foreground": "#47464f",
                "terminal.ansi.black": "#131318",
                "terminal.ansi.bright_black": "#78787b",
                "terminal.ansi.dim_black": "#131318",
                "terminal.ansi.red": "#89374a",
                "terminal.ansi.bright_red": "#ad566b",
                "terminal.ansi.dim_red": "#89374a",
                "terminal.ansi.green": "#266c33",
                "terminal.ansi.bright_green": "#479f58",
                "terminal.ansi.dim_green": "#266c33",
                "terminal.ansi.yellow": "#ad8a2b",
                "terminal.ansi.bright_yellow": "#bc9838",
                "terminal.ansi.dim_yellow": "#ad8a2b",
                "terminal.ansi.blue": "#5c5998",
                "terminal.ansi.bright_blue": "#6c67b0",
                "terminal.ansi.dim_blue": "#5c5998",
                "terminal.ansi.magenta": "#e0deff",
                "terminal.ansi.bright_magenta": "#e0deff",
                "terminal.ansi.dim_magenta": "#e0deff",
                "terminal.ansi.cyan": "#5b5891",
                "terminal.ansi.bright_cyan": "#9997bc",
                "terminal.ansi.dim_cyan": "#5b5891",
                "terminal.ansi.white": "#272628",
                "terminal.ansi.bright_white": "#d5d5d9",
                "terminal.ansi.dim_white": "#272628",
                "link_text.hover": "#5b5891",
                "version_control.added": "#266c33",
                "version_control.modified": "#ad8a2b",
                "version_control.word_added": "#266c3333",
                "version_control.word_deleted": "#89374a33",
                "version_control.deleted": "#89374a",
                "conflict": "#ba1a1a",
                "conflict.background": "#ffdad680",
                "conflict.border": "#410002",
                "created": "#266c33",
                "created.background": "#266c331A",
                "created.border": "#266c33",
                "deleted": "#89374a",
                "deleted.background": "#89374a1A",
                "deleted.border": "#89374a",
                "error": "#ba1a1a",
                "error.background": "#ffdad6",
                "error.border": "#410002",
                "hidden": "#c8c5d0",
                "hidden.background": "#c8c5d01A",
                "hidden.border": "#c8c5d060",
                "hint": "#5b5891",
                "hint.background": "#e3dfff80",
                "hint.border": "#17134a",
                "ignored": "#47464f60",
                "ignored.background": "#e5e1ec40",
                "ignored.border": "#c8c5d040",
                "info": "#5b5891",
                "info.background": "#e3dfff80",
                "info.border": "#17134a",
                "modified": "#ad8a2b",
                "modified.background": "#ad8a2b1A",
                "modified.border": "#ad8a2b",
                "predictive": "#47464f80",
                "predictive.border": "#787680",
                "predictive.background": "#e5e1e980",
                "renamed": "#5c5998",
                "renamed.border": "#5c5998",
                "renamed.background": "#5c59981A",
                "success": "#266c33",
                "success.background": "#266c331A",
                "success.border": "#266c33",
                "unreachable": "#47464f60",
                "unreachable.background": "#e5e1ec40",
                "unreachable.border": "#c8c5d060",
                "warning": "#eab9d1",
                "warning.background": "#ffd8e980",
                "warning.border": "#2f1123",
                "players": [
                    {
                        "cursor": "#5c5998",
                        "background": "#5c599880",
                        "selection": "#5c59983D"
                    },
                    {
                        "cursor": "#89374a",
                        "background": "#89374a80",
                        "selection": "#89374a3D"
                    },
                    {
                        "cursor": "#ad8a2b",
                        "background": "#ad8a2b80",
                        "selection": "#ad8a2b3D"
                    },
                    {
                        "cursor": "#e0deff",
                        "background": "#e0deff80",
                        "selection": "#e0deff3D"
                    },
                    {
                        "cursor": "#5b5891",
                        "background": "#5b589180",
                        "selection": "#5b58913D"
                    },
                    {
                        "cursor": "#ad566b",
                        "background": "#ad566b80",
                        "selection": "#ad566b3D"
                    },
                    {
                        "cursor": "#479f58",
                        "background": "#479f5880",
                        "selection": "#479f583D"
                    },
                    {
                        "cursor": "#266c33",
                        "background": "#266c3380",
                        "selection": "#266c333D"
                    }
                ],
                "syntax": {
                    "attribute": {
                        "color": "#5c5998",
                        "font_style": "italic",
                        "font_weight": null
                    },
                    "boolean": {
                        "color": "#ad566b",
                        "font_style": null,
                        "font_weight": null
                    },
                    "comment": {
                        "color": "#78787b",
                        "font_style": "italic",
                        "font_weight": null
                    },
                    "comment.doc": {
                        "color": "#78787b",
                        "font_style": "italic",
                        "font_weight": null
                    },
                    "constant": {
                        "color": "#ad566b",
                        "font_style": null,
                        "font_weight": null
                    },
                    "constructor": {
                        "color": "#5c5998",
                        "font_style": null,
                        "font_weight": null
                    },
                    "embedded": {
                        "color": "#1c1b21",
                        "font_style": null,
                        "font_weight": null
                    },
                    "emphasis": {
                        "color": "#5c5998",
                        "font_style": "italic",
                        "font_weight": null
                    },
                    "emphasis.strong": {
                        "color": "#ad566b",
                        "font_style": null,
                        "font_weight": 700
                    },
                    "enum": {
                        "color": "#5b5891",
                        "font_style": null,
                        "font_weight": null
                    },
                    "function": {
                        "color": "#5c5998",
                        "font_style": null,
                        "font_weight": null
                    },
                    "keyword": {
                        "color": "#e0deff",
                        "font_style": "italic",
                        "font_weight": null
                    },
                    "label": {
                        "color": "#5c5998",
                        "font_style": null,
                        "font_weight": null
                    },
                    "link_text": {
                        "color": "#5c5998",
                        "font_style": "italic",
                        "font_weight": null
                    },
                    "link_uri": {
                        "color": "#5b5891",
                        "font_style": "normal",
                        "font_weight": null
                    },
                    "number": {
                        "color": "#ad566b",
                        "font_style": null,
                        "font_weight": null
                    },
                    "operator": {
                        "color": "#5b5891",
                        "font_style": null,
                        "font_weight": null
                    },
                    "property": {
                        "color": "#89374a",
                        "font_style": null,
                        "font_weight": null
                    },
                    "punctuation": {
                        "color": "#47464f",
                        "font_style": null,
                        "font_weight": null
                    },
                    "punctuation.bracket": {
                        "color": "#787680",
                        "font_style": null,
                        "font_weight": null
                    },
                    "punctuation.delimiter": {
                        "color": "#787680",
                        "font_style": null,
                        "font_weight": null
                    },
                    "punctuation.list_marker": {
                        "color": "#89374a",
                        "font_style": null,
                        "font_weight": null
                    },
                    "punctuation.special": {
                        "color": "#89374a",
                        "font_style": null,
                        "font_weight": null
                    },
                    "selector": {
                        "color": "#ad8a2b",
                        "font_style": null,
                        "font_weight": null
                    },
                    "selector.pseudo": {
                        "color": "#5c5998",
                        "font_style": null,
                        "font_weight": null
                    },
                    "string": {
                        "color": "#266c33",
                        "font_style": null,
                        "font_weight": null
                    },
                    "string.escape": {
                        "color": "#5b5891",
                        "font_style": null,
                        "font_weight": null
                    },
                    "string.regex": {
                        "color": "#479f58",
                        "font_style": null,
                        "font_weight": null
                    },
                    "string.special": {
                        "color": "#5b5891",
                        "font_style": null,
                        "font_weight": null
                    },
                    "string.special.symbol": {
                        "color": "#5b5891",
                        "font_style": null,
                        "font_weight": null
                    },
                    "tag": {
                        "color": "#5c5998",
                        "font_style": null,
                        "font_weight": null
                    },
                    "text.literal": {
                        "color": "#266c33",
                        "font_style": null,
                        "font_weight": null
                    },
                    "title": {
                        "color": "#89374a",
                        "font_style": null,
                        "font_weight": 700
                    },
                    "type": {
                        "color": "#ad8a2b",
                        "font_style": "italic",
                        "font_weight": null
                    },
                    "variable": {
                        "color": "#1c1b21",
                        "font_style": null,
                        "font_weight": null
                    },
                    "variable.special": {
                        "color": "#ad566b",
                        "font_style": null,
                        "font_weight": null
                    },
                    "variant": {
                        "color": "#5c5998",
                        "font_style": null,
                        "font_weight": null
                    }
                }
            }
        },
        {
            "name": "DankShell Dark Transparent",
            "appearance": "dark",
            "style": {
                "accents": [
                    "#c4c0ff",
                    "#c7c4dc",
                    "#eab9d1"
                ],
                "background.appearance": "blurred",
                "border": "#47464f",
                "border.variant": "#928f99",
                "border.focused": "#c4c0ff",
                "border.selected": "#c4c0ff",
                "border.transparent": null,
                "border.disabled": "#47464f60",
                "elevated_surface.background": "#2a292fB6",
                "surface.background": "#131318B6",
                "background": null,
                "element.background": "#201f25B6",
                "element.hover": "#2a292fB6",
                "element.active": "#35343aB6",
                "element.selected": "#464559B6",
                "element.disabled": "#47464fB6",
                "drop_target.background": "#43407880",
                "ghost_element.background": null,
                "ghost_element.hover": "#201f2580",
                "ghost_element.active": "#2a292fB6",
                "ghost_element.selected": "#46455980",
                "ghost_element.disabled": "#47464f60",
                "text": "#e5e1e9",
                "text.muted": "#c8c5d0",
                "text.placeholder": "#c8c5d099",
                "text.disabled": "#e5e1e960",
                "text.accent": "#c4c0ff",
                "icon": "#e5e1e9",
                "icon.muted": "#c8c5d0",
                "icon.disabled": "#e5e1e960",
                "icon.placeholder": "#c8c5d080",
                "icon.accent": "#c4c0ff",
                "status_bar.background": "#131318B6",
                "title_bar.background": "#131318B6",
                "title_bar.inactive_background": "#131318B6",
                "toolbar.background": "#131318B6",
                "tab_bar.background": "#131318B6",
                "tab.inactive_background": "#131318B6",
                "tab.active_background": "#131318B6",
                "search.match_background": "#ffd87250",
                "search.active_match_background": "#ff9fb566",
                "panel.background": "#131318B6",
                "panel.focused_border": null,
                "pane.focused_border": null,
                "scrollbar.thumb.background": "#c8c5d050",
                "scrollbar.thumb.hover_background": "#c8c5d080",
                "scrollbar.thumb.border": "#47464f40",
                "scrollbar.track.background": null,
                "scrollbar.track.border": "#47464f20",
                "editor.foreground": "#e5e1e9",
                "editor.background": "#131318B6",
                "editor.gutter.background": "#131318B6",
                "editor.subheader.background": "#131318B6",
                "editor.indent_guide": "#47464f22",
                "editor.indent_guide_active": "#c4c0ff99",
                "editor.active_line.background": "#201f2566",
                "editor.highlighted_line.background": "#201f2566",
                "editor.line_number": "#c8c5d0",
                "editor.active_line_number": "#c4c0ff",
                "editor.invisible": "#47464f33",
                "editor.wrap_guide": "#47464f22",
                "editor.active_wrap_guide": "#928f9980",
                "editor.document_highlight.read_background": "#43407860",
                "editor.document_highlight.write_background": "#46455980",
                "terminal.background": "#131318B6",
                "terminal.foreground": "#e5e1e9",
                "terminal.bright_foreground": "#f8f8ff",
                "terminal.dim_foreground": "#c8c5d0",
                "terminal.ansi.black": "#131318",
                "terminal.ansi.bright_black": "#9a99a5",
                "terminal.ansi.dim_black": "#131318",
                "terminal.ansi.red": "#ff7293",
                "terminal.ansi.bright_red": "#ff9fb5",
                "terminal.ansi.dim_red": "#ff7293",
                "terminal.ansi.green": "#7fff97",
                "terminal.ansi.bright_green": "#a5ffb6",
                "terminal.ansi.dim_green": "#7fff97",
                "terminal.ansi.yellow": "#ffd872",
                "terminal.ansi.bright_yellow": "#ffe6a5",
                "terminal.ansi.dim_yellow": "#ffd872",
                "terminal.ansi.blue": "#aeaaf2",
                "terminal.ansi.bright_blue": "#ccc9ff",
                "terminal.ansi.dim_blue": "#aeaaf2",
                "terminal.ansi.magenta": "#434076",
                "terminal.ansi.bright_magenta": "#d5d2ff",
                "terminal.ansi.dim_magenta": "#434076",
                "terminal.ansi.cyan": "#c4c0ff",
                "terminal.ansi.bright_cyan": "#e4e2ff",
                "terminal.ansi.dim_cyan": "#c4c0ff",
                "terminal.ansi.white": "#f0efff",
                "terminal.ansi.bright_white": "#f8f8ff",
                "terminal.ansi.dim_white": "#f0efff",
                "link_text.hover": "#c4c0ff",
                "version_control.added": "#7fff97",
                "version_control.modified": "#ffd872",
                "version_control.word_added": "#7fff9733",
                "version_control.word_deleted": "#ff729333",
                "version_control.deleted": "#ff7293",
                "conflict": "#ffb4ab",
                "conflict.background": "#93000a80",
                "conflict.border": "#ffdad6",
                "created": "#7fff97",
                "created.background": "#7fff971A",
                "created.border": "#7fff97",
                "deleted": "#ff7293",
                "deleted.background": "#ff72931A",
                "deleted.border": "#ff7293",
                "error": "#ffb4ab",
                "error.background": "#93000a",
                "error.border": "#ffdad6",
                "hidden": "#47464f",
                "hidden.background": "#47464f1A",
                "hidden.border": "#47464f60",
                "hint": "#c4c0ff",
                "hint.background": "#43407880",
                "hint.border": "#e3dfff",
                "ignored": "#c8c5d060",
                "ignored.background": "#47464f40",
                "ignored.border": "#47464f40",
                "info": "#c4c0ff",
                "info.background": "#43407880",
                "info.border": "#e3dfff",
                "modified": "#ffd872",
                "modified.background": "#ffd8721A",
                "modified.border": "#ffd872",
                "predictive": "#c8c5d080",
                "predictive.border": "#928f99",
                "predictive.background": "#35343a80",
                "renamed": "#aeaaf2",
                "renamed.border": "#aeaaf2",
                "renamed.background": "#aeaaf21A",
                "success": "#7fff97",
                "success.background": "#7fff971A",
                "success.border": "#7fff97",
                "unreachable": "#c8c5d060",
                "unreachable.background": "#47464f40",
                "unreachable.border": "#47464f60",
                "warning": "#eab9d1",
                "warning.background": "#603b4f80",
                "warning.border": "#ffd8e9",
                "players": [
                    {
                        "cursor": "#aeaaf2",
                        "background": "#aeaaf280",
                        "selection": "#aeaaf23D"
                    },
                    {
                        "cursor": "#ff7293",
                        "background": "#ff729380",
                        "selection": "#ff72933D"
                    },
                    {
                        "cursor": "#ffd872",
                        "background": "#ffd87280",
                        "selection": "#ffd8723D"
                    },
                    {
                        "cursor": "#434076",
                        "background": "#43407680",
                        "selection": "#4340763D"
                    },
                    {
                        "cursor": "#c4c0ff",
                        "background": "#c4c0ff80",
                        "selection": "#c4c0ff3D"
                    },
                    {
                        "cursor": "#ff9fb5",
                        "background": "#ff9fb580",
                        "selection": "#ff9fb53D"
                    },
                    {
                        "cursor": "#a5ffb6",
                        "background": "#a5ffb680",
                        "selection": "#a5ffb63D"
                    },
                    {
                        "cursor": "#7fff97",
                        "background": "#7fff9780",
                        "selection": "#7fff973D"
                    }
                ],
                "syntax": {
                    "attribute": {
                        "color": "#aeaaf2",
                        "font_style": "italic",
                        "font_weight": null
                    },
                    "boolean": {
                        "color": "#ff9fb5",
                        "font_style": null,
                        "font_weight": null
                    },
                    "comment": {
                        "color": "#9a99a5",
                        "font_style": "italic",
                        "font_weight": null
                    },
                    "comment.doc": {
                        "color": "#9a99a5",
                        "font_style": "italic",
                        "font_weight": null
                    },
                    "constant": {
                        "color": "#ff9fb5",
                        "font_style": null,
                        "font_weight": null
                    },
                    "constructor": {
                        "color": "#aeaaf2",
                        "font_style": null,
                        "font_weight": null
                    },
                    "embedded": {
                        "color": "#e5e1e9",
                        "font_style": null,
                        "font_weight": null
                    },
                    "emphasis": {
                        "color": "#aeaaf2",
                        "font_style": "italic",
                        "font_weight": null
                    },
                    "emphasis.strong": {
                        "color": "#ff9fb5",
                        "font_style": null,
                        "font_weight": 700
                    },
                    "enum": {
                        "color": "#c4c0ff",
                        "font_style": null,
                        "font_weight": null
                    },
                    "function": {
                        "color": "#aeaaf2",
                        "font_style": null,
                        "font_weight": null
                    },
                    "keyword": {
                        "color": "#434076",
                        "font_style": "italic",
                        "font_weight": null
                    },
                    "label": {
                        "color": "#aeaaf2",
                        "font_style": null,
                        "font_weight": null
                    },
                    "link_text": {
                        "color": "#aeaaf2",
                        "font_style": "italic",
                        "font_weight": null
                    },
                    "link_uri": {
                        "color": "#c4c0ff",
                        "font_style": "normal",
                        "font_weight": null
                    },
                    "number": {
                        "color": "#ff9fb5",
                        "font_style": null,
                        "font_weight": null
                    },
                    "operator": {
                        "color": "#c4c0ff",
                        "font_style": null,
                        "font_weight": null
                    },
                    "property": {
                        "color": "#ff7293",
                        "font_style": null,
                        "font_weight": null
                    },
                    "punctuation": {
                        "color": "#c8c5d0",
                        "font_style": null,
                        "font_weight": null
                    },
                    "punctuation.bracket": {
                        "color": "#928f99",
                        "font_style": null,
                        "font_weight": null
                    },
                    "punctuation.delimiter": {
                        "color": "#928f99",
                        "font_style": null,
                        "font_weight": null
                    },
                    "punctuation.list_marker": {
                        "color": "#ff7293",
                        "font_style": null,
                        "font_weight": null
                    },
                    "punctuation.special": {
                        "color": "#ff7293",
                        "font_style": null,
                        "font_weight": null
                    },
                    "selector": {
                        "color": "#ffd872",
                        "font_style": null,
                        "font_weight": null
                    },
                    "selector.pseudo": {
                        "color": "#aeaaf2",
                        "font_style": null,
                        "font_weight": null
                    },
                    "string": {
                        "color": "#7fff97",
                        "font_style": null,
                        "font_weight": null
                    },
                    "string.escape": {
                        "color": "#c4c0ff",
                        "font_style": null,
                        "font_weight": null
                    },
                    "string.regex": {
                        "color": "#a5ffb6",
                        "font_style": null,
                        "font_weight": null
                    },
                    "string.special": {
                        "color": "#c4c0ff",
                        "font_style": null,
                        "font_weight": null
                    },
                    "string.special.symbol": {
                        "color": "#c4c0ff",
                        "font_style": null,
                        "font_weight": null
                    },
                    "tag": {
                        "color": "#aeaaf2",
                        "font_style": null,
                        "font_weight": null
                    },
                    "text.literal": {
                        "color": "#7fff97",
                        "font_style": null,
                        "font_weight": null
                    },
                    "title": {
                        "color": "#ff7293",
                        "font_style": null,
                        "font_weight": 700
                    },
                    "type": {
                        "color": "#ffd872",
                        "font_style": "italic",
                        "font_weight": null
                    },
                    "variable": {
                        "color": "#e5e1e9",
                        "font_style": null,
                        "font_weight": null
                    },
                    "variable.special": {
                        "color": "#ff9fb5",
                        "font_style": null,
                        "font_weight": null
                    },
                    "variant": {
                        "color": "#aeaaf2",
                        "font_style": null,
                        "font_weight": null
                    }
                }
            }
        },
        {
            "name": "DankShell Light Transparent",
            "appearance": "light",
            "style": {
                "accents": [
                    "#5b5891",
                    "#5e5c71",
                    "#7a5367"
                ],
                "background.appearance": "blurred",
                "border": "#c8c5d0",
                "border.variant": "#787680",
                "border.focused": "#5b5891",
                "border.selected": "#5b5891",
                "border.transparent": null,
                "border.disabled": "#c8c5d060",
                "elevated_surface.background": "#ebe7efB6",
                "surface.background": "#fcf8ffB6",
                "background": null,
                "element.background": "#f0ecf4B6",
                "element.hover": "#ebe7efB6",
                "element.active": "#e5e1e9B6",
                "element.selected": "#e3e0f9B6",
                "element.disabled": "#e5e1ecB6",
                "drop_target.background": "#e3dfff80",
                "ghost_element.background": null,
                "ghost_element.hover": "#f0ecf480",
                "ghost_element.active": "#ebe7efB6",
                "ghost_element.selected": "#e3e0f980",
                "ghost_element.disabled": "#e5e1ec60",
                "text": "#1c1b21",
                "text.muted": "#47464f",
                "text.placeholder": "#47464f99",
                "text.disabled": "#1c1b2160",
                "text.accent": "#5b5891",
                "icon": "#1c1b21",
                "icon.muted": "#47464f",
                "icon.disabled": "#1c1b2160",
                "icon.placeholder": "#47464f80",
                "icon.accent": "#5b5891",
                "status_bar.background": "#dcd8e0B6",
                "title_bar.background": "#dcd8e0B6",
                "title_bar.inactive_background": "#dcd8e0B6",
                "toolbar.background": "#fcf8ffB6",
                "tab_bar.background": "#fcf8ffB6",
                "tab.inactive_background": "#fcf8ffB6",
                "tab.active_background": "#fcf8ffB6",
                "search.match_background": "#ad8a2b50",
                "search.active_match_background": "#ad566b66",
                "panel.background": "#fcf8ffB6",
                "panel.focused_border": null,
                "pane.focused_border": null,
                "scrollbar.thumb.background": "#47464f50",
                "scrollbar.thumb.hover_background": "#47464fC0",
                "scrollbar.thumb.border": "#c8c5d040",
                "scrollbar.track.background": null,
                "scrollbar.track.border": "#c8c5d020",
                "editor.foreground": "#1c1b21",
                "editor.background": "#fcf8ffB6",
                "editor.gutter.background": "#dcd8e0B6",
                "editor.subheader.background": "#fcf8ffB6",
                "editor.indent_guide": "#c8c5d022",
                "editor.indent_guide_active": "#78768099",
                "editor.active_line.background": "#f0ecf466",
                "editor.highlighted_line.background": "#f0ecf466",
                "editor.line_number": "#47464f",
                "editor.active_line_number": "#5b5891",
                "editor.invisible": "#c8c5d033",
                "editor.wrap_guide": "#c8c5d022",
                "editor.active_wrap_guide": "#78768080",
                "editor.document_highlight.read_background": "#e3dfff60",
                "editor.document_highlight.write_background": "#e3e0f980",
                "terminal.background": "#fcf8ffB6",
                "terminal.foreground": "#1c1b21",
                "terminal.bright_foreground": "#d5d5d9",
                "terminal.dim_foreground": "#47464f",
                "terminal.ansi.black": "#131318",
                "terminal.ansi.bright_black": "#78787b",
                "terminal.ansi.dim_black": "#131318",
                "terminal.ansi.red": "#89374a",
                "terminal.ansi.bright_red": "#ad566b",
                "terminal.ansi.dim_red": "#89374a",
                "terminal.ansi.green": "#266c33",
                "terminal.ansi.bright_green": "#479f58",
                "terminal.ansi.dim_green": "#266c33",
                "terminal.ansi.yellow": "#ad8a2b",
                "terminal.ansi.bright_yellow": "#bc9838",
                "terminal.ansi.dim_yellow": "#ad8a2b",
                "terminal.ansi.blue": "#5c5998",
                "terminal.ansi.bright_blue": "#6c67b0",
                "terminal.ansi.dim_blue": "#5c5998",
                "terminal.ansi.magenta": "#e0deff",
                "terminal.ansi.bright_magenta": "#e0deff",
                "terminal.ansi.dim_magenta": "#e0deff",
                "terminal.ansi.cyan": "#5b5891",
                "terminal.ansi.bright_cyan": "#9997bc",
                "terminal.ansi.dim_cyan": "#5b5891",
                "terminal.ansi.white": "#272628",
                "terminal.ansi.bright_white": "#d5d5d9",
                "terminal.ansi.dim_white": "#272628",
                "link_text.hover": "#5b5891",
                "version_control.added": "#266c33",
                "version_control.modified": "#ad8a2b",
                "version_control.word_added": "#266c3333",
                "version_control.word_deleted": "#89374a33",
                "version_control.deleted": "#89374a",
                "conflict": "#ba1a1a",
                "conflict.background": "#ffdad680",
                "conflict.border": "#410002",
                "created": "#266c33",
                "created.background": "#266c331A",
                "created.border": "#266c33",
                "deleted": "#89374a",
                "deleted.background": "#89374a1A",
                "deleted.border": "#89374a",
                "error": "#ba1a1a",
                "error.background": "#ffdad6",
                "error.border": "#410002",
                "hidden": "#c8c5d0",
                "hidden.background": "#c8c5d01A",
                "hidden.border": "#c8c5d060",
                "hint": "#5b5891",
                "hint.background": "#e3dfff80",
                "hint.border": "#17134a",
                "ignored": "#47464f60",
                "ignored.background": "#e5e1ec40",
                "ignored.border": "#c8c5d040",
                "info": "#5b5891",
                "info.background": "#e3dfff80",
                "info.border": "#17134a",
                "modified": "#ad8a2b",
                "modified.background": "#ad8a2b1A",
                "modified.border": "#ad8a2b",
                "predictive": "#47464f80",
                "predictive.border": "#787680",
                "predictive.background": "#e5e1e980",
                "renamed": "#5c5998",
                "renamed.border": "#5c5998",
                "renamed.background": "#5c59981A",
                "success": "#266c33",
                "success.background": "#266c331A",
                "success.border": "#266c33",
                "unreachable": "#47464f60",
                "unreachable.background": "#e5e1ec40",
                "unreachable.border": "#c8c5d060",
                "warning": "#eab9d1",
                "warning.background": "#ffd8e980",
                "warning.border": "#2f1123",
                "players": [
                    {
                        "cursor": "#5c5998",
                        "background": "#5c599880",
                        "selection": "#5c59983D"
                    },
                    {
                        "cursor": "#89374a",
                        "background": "#89374a80",
                        "selection": "#89374a3D"
                    },
                    {
                        "cursor": "#ad8a2b",
                        "background": "#ad8a2b80",
                        "selection": "#ad8a2b3D"
                    },
                    {
                        "cursor": "#e0deff",
                        "background": "#e0deff80",
                        "selection": "#e0deff3D"
                    },
                    {
                        "cursor": "#5b5891",
                        "background": "#5b589180",
                        "selection": "#5b58913D"
                    },
                    {
                        "cursor": "#ad566b",
                        "background": "#ad566b80",
                        "selection": "#ad566b3D"
                    },
                    {
                        "cursor": "#479f58",
                        "background": "#479f5880",
                        "selection": "#479f583D"
                    },
                    {
                        "cursor": "#266c33",
                        "background": "#266c3380",
                        "selection": "#266c333D"
                    }
                ],
                "syntax": {
                    "attribute": {
                        "color": "#5c5998",
                        "font_style": "italic",
                        "font_weight": null
                    },
                    "boolean": {
                        "color": "#ad566b",
                        "font_style": null,
                        "font_weight": null
                    },
                    "comment": {
                        "color": "#78787b",
                        "font_style": "italic",
                        "font_weight": null
                    },
                    "comment.doc": {
                        "color": "#78787b",
                        "font_style": "italic",
                        "font_weight": null
                    },
                    "constant": {
                        "color": "#ad566b",
                        "font_style": null,
                        "font_weight": null
                    },
                    "constructor": {
                        "color": "#5c5998",
                        "font_style": null,
                        "font_weight": null
                    },
                    "embedded": {
                        "color": "#1c1b21",
                        "font_style": null,
                        "font_weight": null
                    },
                    "emphasis": {
                        "color": "#5c5998",
                        "font_style": "italic",
                        "font_weight": null
                    },
                    "emphasis.strong": {
                        "color": "#ad566b",
                        "font_style": null,
                        "font_weight": 700
                    },
                    "enum": {
                        "color": "#5b5891",
                        "font_style": null,
                        "font_weight": null
                    },
                    "function": {
                        "color": "#5c5998",
                        "font_style": null,
                        "font_weight": null
                    },
                    "keyword": {
                        "color": "#e0deff",
                        "font_style": "italic",
                        "font_weight": null
                    },
                    "label": {
                        "color": "#5c5998",
                        "font_style": null,
                        "font_weight": null
                    },
                    "link_text": {
                        "color": "#5c5998",
                        "font_style": "italic",
                        "font_weight": null
                    },
                    "link_uri": {
                        "color": "#5b5891",
                        "font_style": "normal",
                        "font_weight": null
                    },
                    "number": {
                        "color": "#ad566b",
                        "font_style": null,
                        "font_weight": null
                    },
                    "operator": {
                        "color": "#5b5891",
                        "font_style": null,
                        "font_weight": null
                    },
                    "property": {
                        "color": "#89374a",
                        "font_style": null,
                        "font_weight": null
                    },
                    "punctuation": {
                        "color": "#47464f",
                        "font_style": null,
                        "font_weight": null
                    },
                    "punctuation.bracket": {
                        "color": "#787680",
                        "font_style": null,
                        "font_weight": null
                    },
                    "punctuation.delimiter": {
                        "color": "#787680",
                        "font_style": null,
                        "font_weight": null
                    },
                    "punctuation.list_marker": {
                        "color": "#89374a",
                        "font_style": null,
                        "font_weight": null
                    },
                    "punctuation.special": {
                        "color": "#89374a",
                        "font_style": null,
                        "font_weight": null
                    },
                    "selector": {
                        "color": "#ad8a2b",
                        "font_style": null,
                        "font_weight": null
                    },
                    "selector.pseudo": {
                        "color": "#5c5998",
                        "font_style": null,
                        "font_weight": null
                    },
                    "string": {
                        "color": "#266c33",
                        "font_style": null,
                        "font_weight": null
                    },
                    "string.escape": {
                        "color": "#5b5891",
                        "font_style": null,
                        "font_weight": null
                    },
                    "string.regex": {
                        "color": "#479f58",
                        "font_style": null,
                        "font_weight": null
                    },
                    "string.special": {
                        "color": "#5b5891",
                        "font_style": null,
                        "font_weight": null
                    },
                    "string.special.symbol": {
                        "color": "#5b5891",
                        "font_style": null,
                        "font_weight": null
                    },
                    "tag": {
                        "color": "#5c5998",
                        "font_style": null,
                        "font_weight": null
                    },
                    "text.literal": {
                        "color": "#266c33",
                        "font_style": null,
                        "font_weight": null
                    },
                    "title": {
                        "color": "#89374a",
                        "font_style": null,
                        "font_weight": 700
                    },
                    "type": {
                        "color": "#ad8a2b",
                        "font_style": "italic",
                        "font_weight": null
                    },
                    "variable": {
                        "color": "#1c1b21",
                        "font_style": null,
                        "font_weight": null
                    },
                    "variable.special": {
                        "color": "#ad566b",
                        "font_style": null,
                        "font_weight": null
                    },
                    "variant": {
                        "color": "#5c5998",
                        "font_style": null,
                        "font_weight": null
                    }
                }
            }
        }
    ]
}
